intel_extension_for_tensorflow/__init__.py
intel_extension_for_tensorflow/__main__.py
intel_extension_for_tensorflow/core/utils/protobuf/__init__.py
intel_extension_for_tensorflow/core/utils/protobuf/config_pb2.py
intel_extension_for_tensorflow/python/__init__.py
intel_extension_for_tensorflow/python/config.py
intel_extension_for_tensorflow/python/device.py
intel_extension_for_tensorflow/python/experimental_ops_override.py
intel_extension_for_tensorflow/python/gen_itex_version.py
intel_extension_for_tensorflow/python/launch.py
intel_extension_for_tensorflow/python/version.py
intel_extension_for_tensorflow/python/distribute/__init__.py
intel_extension_for_tensorflow/python/distribute/cross_device_ops.py
intel_extension_for_tensorflow/python/fp8/__init__.py
intel_extension_for_tensorflow/python/fp8/autocast.py
intel_extension_for_tensorflow/python/fp8/recipe.py
intel_extension_for_tensorflow/python/ops/__init__.py
intel_extension_for_tensorflow/python/ops/activations.py
intel_extension_for_tensorflow/python/ops/beam_select.py
intel_extension_for_tensorflow/python/ops/collective_ops.py
intel_extension_for_tensorflow/python/ops/group_norm.py
intel_extension_for_tensorflow/python/ops/layer_norm.py
intel_extension_for_tensorflow/python/ops/load_ops_library.py
intel_extension_for_tensorflow/python/ops/mlp.py
intel_extension_for_tensorflow/python/ops/multi_head_attention.py
intel_extension_for_tensorflow/python/ops/ops_grad.py
intel_extension_for_tensorflow/python/ops/optimizers.py
intel_extension_for_tensorflow/python/ops/recurrent.py
intel_extension_for_tensorflow/python/ops/rms_norm.py
intel_extension_for_tensorflow/python/ops/rotary_embedding.py
intel_extension_for_tensorflow/python/optimize/quantization.py
intel_extension_for_tensorflow/python/test_func/__init__.py
intel_extension_for_tensorflow/python/test_func/eager_test.py
intel_extension_for_tensorflow/python/test_func/keras_parameterized.py
intel_extension_for_tensorflow/python/test_func/keras_testing_utils.py
intel_extension_for_tensorflow-2.15.0.3.dist-info/LICENSE.txt
intel_extension_for_tensorflow-2.15.0.3.dist-info/METADATA
intel_extension_for_tensorflow-2.15.0.3.dist-info/WHEEL
intel_extension_for_tensorflow-2.15.0.3.dist-info/top_level.txt
intel_extension_for_tensorflow-2.15.0.3.dist-info/RECORD
